LICENSE
nonebot_plugin_group_event/__init__.py
nonebot_plugin_group_event/config.py
nonebot_plugin_group_event/poke.py
README.md
nonebot_plugin_group_event-0.0.1.dist-info/LICENSE
nonebot_plugin_group_event-0.0.1.dist-info/METADATA
nonebot_plugin_group_event-0.0.1.dist-info/WHEEL
nonebot_plugin_group_event-0.0.1.dist-info/RECORD
