Metadata-Version: 2.1
Name: nonebot-plugin-group-event
Version: 0.0.1
Summary: NoneBot2插件，群聊事件交互
Home-page: https://github.com/Agnes4m/nonebot_plugin_group_event
License: MIT
Keywords: game,nonebot2,plugin,bilibili
Author: Agnes_Digital
Author-email: Z735803792@163.com
Requires-Python: >=3.9,<4.0
Classifier: License :: OSI Approved :: MIT License
Classifier: Operating System :: OS Independent
Classifier: Programming Language :: Python
Classifier: Programming Language :: Python :: 3
Classifier: Programming Language :: Python :: 3.9
Classifier: Programming Language :: Python :: 3.10
Classifier: Programming Language :: Python :: 3.11
Classifier: Programming Language :: Python :: 3
Classifier: Programming Language :: Python :: 3.10
Classifier: Programming Language :: Python :: 3.9
Requires-Dist: nonebot-adapter-onebot (>=2.2.1)
Requires-Dist: nonebot2 (>=2.0.0,<3.0.0)
Requires-Dist: ruamel.yaml (>=0.17.21,<0.18.0)
Project-URL: Repository, https://github.com/Agnes4m/nonebot_plugin_group_event
